torrechess/__init__.py
torrechess/heuristic_engines.py
torrechess/neural_engines.py
torrechess/utils.py
torrechess-0.0.5.dist-info/LICENSE
torrechess-0.0.5.dist-info/METADATA
torrechess-0.0.5.dist-info/WHEEL
torrechess-0.0.5.dist-info/top_level.txt
torrechess-0.0.5.dist-info/RECORD
