Metadata-Version: 2.1
Name: torrechess
Version: 0.0.5
Summary: Playing around with neural networks and funny chess engines
Author-email: Riccardo Torreggiani <riccardo.torreggiani@gmail.com>
Project-URL: Homepage, https://github.com/rktr1998/torrechess
Project-URL: Issues, https://github.com/rktr1998/torrechess/issues
Classifier: Programming Language :: Python :: 3
Classifier: License :: OSI Approved :: MIT License
Classifier: Operating System :: OS Independent
Requires-Python: >=3.8
License-File: LICENSE
